arimafd/__init__.py
arimafd/diff_integ.py
arimafd/find_best_model.py
arimafd/main.py
arimafd/tanh.py
arimafd-1.4.1.dist-info/LICENSE
arimafd-1.4.1.dist-info/METADATA
arimafd-1.4.1.dist-info/WHEEL
arimafd-1.4.1.dist-info/top_level.txt
arimafd-1.4.1.dist-info/RECORD
