Metadata-Version: 2.1
Name: arimafd
Version: 1.4.1
Summary: Build librarry
Home-page: https://github.com/waico/arimafd
Author: Vyacheslav Kozitsin, Iurii Katser
Author-email: waico@waico.ru
License: MIT
Platform: UNKNOWN
Requires-Dist: numpy
Requires-Dist: pandas
Requires-Dist: sympy
Requires-Dist: sklearn
Requires-Dist: statsmodels
